json2any/DataLoaderException.py
json2any/JSONSchemaWithUnion.py
json2any/JinjaExecutor.py
json2any/Json2AnyException.py
json2any/ProviderPlugins.py
json2any/__init__.py
json2any/cli_logg_utils.py
json2any/cli/__init__.py
json2any/cli/cmd_dump_schema.py
json2any/cli/cmd_run.py
json2any/cli/main.py
json2any/data_provider/EnvDataProvider.py
json2any/data_provider/JSONDataProvider.py
json2any/data_provider/__init__.py
json2any/helper_provider/ExampleHelperProvider.py
json2any/helper_provider/__init__.py
json2any/project/CopyDescriptor.py
json2any/project/Json2AnyDescriptor.py
json2any/project/RenderDescriptor.py
json2any/project/__init__.py
json2any/resources/json2any.schema.json
json2any/resources/rds.schema.json
json2any/template_provider/FileSystemTemplateProvider.py
json2any/template_provider/__init__.py
json2any-1.0.0.dist-info/METADATA
json2any-1.0.0.dist-info/WHEEL
json2any-1.0.0.dist-info/entry_points.txt
json2any-1.0.0.dist-info/RECORD
