Metadata-Version: 2.4
Name: json2any
Version: 1.0.0
Summary: JSON template generator
Author-email: Maciej Matuszak <maciej.matuszak@gmail.com>
License-Expression: MIT
Requires-Python: >=3.8
Requires-Dist: json2any-plugin>=1.1.0
Requires-Dist: jsonpath-ng>=1.7.0
Requires-Dist: marshmallow-dataclass>=8.7.1
Requires-Dist: marshmallow-jsonschema>=0.13.0
Requires-Dist: marshmallow-union>=0.1.15.post1
Requires-Dist: marshmallow[union]>=3.22.0
Requires-Dist: setuptools>=75.3.2
